mpimap/__init__.py
mpimap/mpimap.py
mpimap-1.0.4.dist-info/METADATA
mpimap-1.0.4.dist-info/RECORD
mpimap-1.0.4.dist-info/WHEEL
mpimap-1.0.4.dist-info/top_level.txt
