Metadata-Version: 2.1
Name: mpimap
Version: 1.0.4
Summary: Parallel function mapping using mpi4py
Home-page: http://gitlab.com/Wokpak/mpimap
Author: Jed Hollom
Author-email: Jedhollom@gmail.com
License: UNKNOWN
Platform: UNKNOWN
Classifier: Programming Language :: Python :: 2.7
Classifier: License :: OSI Approved :: MIT License
Classifier: Operating System :: OS Independent
Requires-Dist: multiprocessing
Requires-Dist: mpi4py
Requires-Dist: dill
